Workbook

Sheet TOP SHEET
A1: PRODUCTION BUDGET — TOP SHEET
A2: Category | B2: Account(s) | C2: Total
A3: ABOVE THE LINE
A4: Development + Story & Rights | C4: =SUM('1100'!H:H,'1200'!H:H) -> 0
A5: Producers Unit | C5: =SUM('1400'!H:H) -> 0
A6: Directors Unit | C6: =SUM('1500'!H:H) -> 0
A7: Talent / Cast | C7: =SUM('1600'!H:H) -> #VALUE!
A8: TOTAL ABOVE THE LINE | C8: =SUM(C4:C7) -> #VALUE!
A10: BELOW THE LINE
A11: Production Staff | C11: =SUM('2100'!H:H) -> 0
A12: Art Direction + Set Construction + Set Decoration | C12: =SUM('2200'!H:H,'2300'!H:H,'2400'!H:H) -> #VALUE!
A13: Props | C13: =SUM('2500'!H:H) -> #VALUE!
A14: Camera | C14: =SUM('2600'!H:H) -> #VALUE!
A15: Electric | C15: =SUM('2700'!H:H) -> #VALUE!
A16: Grip | C16: =SUM('2800'!H:H) -> 0
A17: Production Sound | C17: =SUM('2900'!H:H) -> 0
A18: Mechanical FX + Special VFX | C18: =SUM('3000'!H:H,'3100'!H:H) -> #VALUE!
A19: Set Operations | C19: =SUM('3200'!H:H) -> 0
A20: Wardrobe | C20: =SUM('3300'!H:H) -> #VALUE!
A21: Makeup & Hair | C21: =SUM('3400'!H:H) -> #VALUE!
A22: Locations | C22: =SUM('3500'!H:H) -> #VALUE!
A23: Transportation | C23: =SUM('3600'!H:H) -> 0
A24: Studio Facilities + Atmosphere | C24: =SUM('3800'!H:H,'3900'!H:H) -> 0
A25: TOTAL BELOW THE LINE | C25: =SUM(C11:C24) -> #VALUE!
A27: POST PRODUCTION
A28: Editing + Post Film/Lab + Post Sound + Music + Titles + Opticals + Post Video | C28: =SUM('5100'!H:H,'5200'!H:H,'5300'!H:H,'5400'!H:H,'5500'!H:H,'5600'!H:H,'5700'!H:H) -> 0
A29: TOTAL POST PRODUCTION | C29: =SUM(C28) -> 0
A31: OTHER
A32: Insurance | C32: =SUM('6100'!H:H) -> 0
A33: Legal | C33: =SUM('6200'!H:H) -> 0
A34: Publicity | C34: =SUM('6300'!H:H) -> 0
A35: Contingency (10%) | C35: =(C8+C25+C29)*0.1 -> #VALUE!
A36: GRAND TOTAL | C36: =C8+C25+C29+C32+C33+C34+C35 -> #VALUE!

Sheet SCENE BREAKDOWN
A1: Scene # | B1: Scene Heading | C1: Int/Ext | D1: Day/Night | E1: Page Count | F1: Script Day | G1: Cast | H1: Extras / Background | I1: Props | J1: Practical FX | K1: Wardrobe | L1: Animals | M1: Vehicles / Picture Cars | N1: Special Makeup | O1: Special Camera | P1: Stunts | Q1: VFX | R1: Location Type | S1: Shooting Day | T1: Est. Shoot Hours | U1: Notes / Flags | V1: Script Page
A2: 1 | B2: EXT. CHURCH – NIGHT | C2: EXT | D2: NIGHT | E2: 3/8 | F2: Day 1 | G2: MAN BROTHER | I2: cigarette church door keys | K2: Man: disheveled, raggy clothes; Brother: religious habit/brother's attire | O2: wide/long take setup | R2: Practical | S2: [SCHEDULE] | T2: [SCHEDULE] | U2: NIGHT shoot – night lighting package required EXT public space – location permit required | V2: 2
A3: 2 | B3: INT. CHURCH ENTRANCE – CONTINUOUS | C3: INT | D3: NIGHT | E3: 2/8 | F3: Day 1 | G3: MAN | I3: lock pick tools (implied) | K3: Man: disheveled, raggy clothes, poorly shaven | N3: disheveled/sweating makeup for Man | O3: handheld camera | R3: Practical | S3: [SCHEDULE] | T3: [SCHEDULE] | U3: NIGHT shoot – night lighting package required | V3: 2
A4: 3 | B4: EXT. CHURCH – CONTINUOUS | C4: EXT | D4: NIGHT | E4: 1/8 | F4: Day 1 | G4: BROTHER | K4: Brother: religious habit/brother's attire | O4: static shot | R4: Practical | S4: [SCHEDULE] | T4: [SCHEDULE] | U4: NIGHT shoot – night lighting package required EXT public space – location permit required | V4: 2
A5: 4 | B5: INT. CHURCH – CONTINUOUS | C5: INT | D5: NIGHT | E5: 6/8 | F5: Day 1 | G5: MAN BROTHER | I5: donation box (breakaway/smashable) scattered money/cash bag pocket knife (dollar-store) rosary crucifix on wall | J5: smashing donation box | K5: Man: disheveled, raggy clothes; Brother: religious habit/brother's attire | N5: Man: sweating, tear-up effect | O5: dim interior lighting setup depth-of-field background focus pull | P5: Brother grabs Man's shoulders – physical contact between actors Man bolts and is stopped by Brother – physical restraint | R5: Practical | S5: [SCHEDULE] | T5: [SCHEDULE] | U5: NIGHT shoot – night lighting package required Weapon (pocket knife) – armorer required Physical contact between actors – stunt coordinator required | V5: 2

Sheet 1100
A1: Account No | B1: Description | C1: Amount | D1: Unit Type | E1: Rate | F1: Subtotal | G1: Fringe % | H1: Total | I1: Vendor | J1: Vendor URL | K1: Script Page | L1: Script Quote | M1: Notes | N1: Confidence | O1: Populated By
A2: 1100.01 | B2: Story option / rights acquisition | C2: [DEAL] | O2: DEAL
A3: 1100.02 | B3: Screenplay development fee | C3: [DEAL] | O3: DEAL
A4: 1100.03 | B4: Development legal | C4: [DEAL] | O4: DEAL
A5: 1100.04 | B5: Development overhead | C5: [DEAL] | O5: DEAL

Sheet 1200
A1: Account No | B1: Description | C1: Amount | D1: Unit Type | E1: Rate | F1: Subtotal | G1: Fringe % | H1: Total | I1: Vendor | J1: Vendor URL | K1: Script Page | L1: Script Quote | M1: Notes | N1: Confidence | O1: Populated By
A2: 1200.01 | B2: Story rights purchase | C2: [DEAL] | O2: DEAL
A3: 1200.02 | B3: Writer fee | C3: [DEAL] | O3: DEAL
A4: 1200.03 | B4: Continuity / breakdown | C4: [DEAL] | O4: DEAL
A5: 1200.04 | B5: Script duplication | C5: [DEAL] | O5: DEAL

Sheet 1400
A1: Account No | B1: Description | C1: Amount | D1: Unit Type | E1: Rate | F1: Subtotal | G1: Fringe % | H1: Total | I1: Vendor | J1: Vendor URL | K1: Script Page | L1: Script Quote | M1: Notes | N1: Confidence | O1: Populated By
A2: 1400.01 | B2: Executive Producer fee | C2: [DEAL] | O2: DEAL
A3: 1400.02 | B3: Producer fee | C3: [DEAL] | O3: DEAL
A4: 1400.03 | B4: Line Producer fee | C4: [DEAL] | O4: DEAL
A5: 1400.04 | B5: Producer assistant(s) | C5: [DEAL] | O5: DEAL

Sheet 1500
A1: Account No | B1: Description | C1: Amount | D1: Unit Type | E1: Rate | F1: Subtotal | G1: Fringe % | H1: Total | I1: Vendor | J1: Vendor URL | K1: Script Page | L1: Script Quote | M1: Notes | N1: Confidence | O1: Populated By
A2: 1500.01 | B2: Director fee | C2: [DEAL] | O2: DEAL
A3: 1500.02 | B3: Director assistant | C3: [DEAL] | O3: DEAL
A4: 1500.03 | B4: Storyboard artist | C4: [DEAL] | O4: DEAL

Sheet 1600
A1: Account No | B1: Description | C1: Amount | D1: Unit Type | E1: Rate | F1: Subtotal | G1: Fringe % | H1: Total | I1: Vendor | J1: Vendor URL | K1: Script Page | L1: Script Quote | M1: Notes | N1: Confidence | O1: Populated By
A2: 1600.01 | B2: MAN – Lead Cast | C2: 4 | D2: Days | F2: =C2*D2*E2 -> #VALUE! | H2: =F2+(F2*G2) -> #VALUE! | K2: 2 | L2: A MAN lurks in the shadows of the church wall. | M2: Appears in all 4 scenes. Principal role; carries entire dramatic arc of script. | N2: High | O2: SCRIPT
A3: 1600.02 | B3: BROTHER – Supporting Cast | C3: 3 | D3: Days | F3: =C3*D3*E3 -> #VALUE! | H3: =F3+(F3*G3) -> #VALUE! | K3: 2 | L3: A BROTHER emerges from the church, locks the door with his keys. | M3: Appears in scenes 1, 3, and 4. Key supporting role with significant dialogue and physical action. | N3: High | O3: SCRIPT
A4: 1600.03 | B4: Casting Director | C4: [DEAL] | O4: DEAL
A5: 1600.04 | B5: Casting Associate | C5: [DEAL] | O5: DEAL

Sheet 2100
A1: Account No | B1: Description | C1: Amount | D1: Unit Type | E1: Rate | F1: Subtotal | G1: Fringe % | H1: Total | I1: Vendor | J1: Vendor URL | K1: Script Page | L1: Script Quote | M1: Notes | N1: Confidence | O1: Populated By
A2: 2100.01 | B2: Production Manager / UPM | C2: [SCHEDULE] | O2: SCHEDULE
A3: 2100.02 | B3: 1st Assistant Director | C3: [SCHEDULE] | O3: SCHEDULE
A4: 2100.03 | B4: 2nd Assistant Director | C4: [SCHEDULE] | O4: SCHEDULE
A5: 2100.04 | B5: Production Coordinator | C5: [SCHEDULE] | O5: SCHEDULE
A6: 2100.05 | B6: Production Secretary | C6: [SCHEDULE] | O6: SCHEDULE
A7: 2100.06 | B7: Location Manager | C7: [SCHEDULE] | O7: SCHEDULE
A8: 2100.07 | B8: Production Accountant | C8: [SCHEDULE] | O8: SCHEDULE
A9: 2100.08 | B9: Payroll services | C9: [DEAL] | O9: DEAL

Sheet 2200
A1: Account No | B1: Description | C1: Amount | D1: Unit Type | E1: Rate | F1: Subtotal | G1: Fringe % | H1: Total | I1: Vendor | J1: Vendor URL | K1: Script Page | L1: Script Quote | M1: Notes | N1: Confidence | O1: Populated By
A2: 2200.01 | B2: Art Direction - Church interior set dressing (donation box, crucifix, pews/aisle) | C2: 1 | D2: Allow | F2: =C2*D2*E2 -> #VALUE! | H2: =F2+(F2*G2) -> #VALUE! | K2: 2 | L2: He finds the donation box, struggles to pry it open, then smashes it | M2: Donation box must be practical/breakaway for smashing action. Crucifix hero prop on wall. Church interior dressing required. | N2: High | O2: SCRIPT
A3: 2200.02 | B3: Art Direction - Breakaway donation box (practical destructible prop) | C3: 3 | D3: Purchase | F3: =C3*D3*E3 -> #VALUE! | H3: =F3+(F3*G3) -> #VALUE! | K3: 2 | L3: struggles to pry it open, then smashes it in frustration. Money scatters | M3: Multiple units needed for takes. Must shatter convincingly and scatter prop money. | N3: High | O3: SCRIPT
A4: 2200.03 | B4: Art Direction - Prop money (scattered currency) | C4: 1 | D4: Allow | F4: =C4*D4*E4 -> #VALUE! | H4: =F4+(F4*G4) -> #VALUE! | K4: 2 | L4: Money scatters across the floor. He crouches to collect it. | M4: Prop money sufficient to fill donation box and scatter across floor. Not legal tender. | N4: High | O4: SCRIPT
A5: 2200.04 | B5: Production Designer | C5: [DEAL] | O5: DEAL
A6: 2200.05 | B6: Art Director | C6: [DEAL] | O6: DEAL
A7: 2200.06 | B7: Set Designer / Drafting | C7: [DEAL] | O7: DEAL
A8: 2200.07 | B8: Art Department Assistant | C8: [DEAL] | O8: DEAL
A9: 2200.08 | B9: Art Department supplies | C9: [DEAL] | O9: DEAL

Sheet 2300
A1: Account No | B1: Description | C1: Amount | D1: Unit Type | E1: Rate | F1: Subtotal | G1: Fringe % | H1: Total | I1: Vendor | J1: Vendor URL | K1: Script Page | L1: Script Quote | M1: Notes | N1: Confidence | O1: Populated By
A2: 2300.01 | B2: Set Construction / Location Prep - Church exterior (practical location or build) | C2: 1 | D2: Allow | F2: =C2*D2*E2 -> #VALUE! | H2: =F2+(F2*G2) -> #VALUE! | K2: 2 | L2: A small church sits still under streetlight. | M2: Practical church location preferred. Exterior and interior required. Lock/door mechanism must be functional for lock-picking action. | N2: High | O2: SCRIPT
A3: 2300.02 | B3: Construction Coordinator | C3: [DEAL] | O3: DEAL
A4: 2300.03 | B4: Construction labor | C4: [DEAL] | O4: DEAL
A5: 2300.04 | B5: Construction materials | C5: [DEAL] | O5: DEAL
A6: 2300.05 | B6: Stage / mill rental | C6: [DEAL] | O6: DEAL

Sheet 2400
A1: Account No | B1: Description | C1: Amount | D1: Unit Type | E1: Rate | F1: Subtotal | G1: Fringe % | H1: Total | I1: Vendor | J1: Vendor URL | K1: Script Page | L1: Script Quote | M1: Notes | N1: Confidence | O1: Populated By
A2: 2400.01 | B2: Special Effects / Property - Lock-pick practical gag (church door lock) | C2: 1 | D2: Allow | F2: =C2*D2*E2 -> #VALUE! | H2: =F2+(F2*G2) -> #VALUE! | K2: 2 | L2: Close-ups of hands picking the locks. Opens the door. Closes the door. | M2: Practical lock and pick set required for close-up hero shots. May require duplicates for multiple takes. | N2: High | O2: SCRIPT
A3: 2400.02 | B3: Set Decorator | C3: [DEAL] | O3: DEAL
A4: 2400.03 | B4: Swing Gang | C4: [DEAL] | O4: DEAL
A5: 2400.04 | B5: Set dressings — purchased | C5: [DEAL] | O5: DEAL
A6: 2400.05 | B6: Set dressings — rented | C6: [DEAL] | O6: DEAL
A7: 2400.06 | B7: Graphics / signage | C7: [DEAL] | O7: DEAL

Sheet 2500
A1: Account No | B1: Description | C1: Amount | D1: Unit Type | E1: Rate | F1: Subtotal | G1: Fringe % | H1: Total | I1: Vendor | J1: Vendor URL | K1: Script Page | L1: Script Quote | M1: Notes | N1: Confidence | O1: Populated By
A2: 2500.01 | B2: Props - Pocket knife (dollar-store prop knife, hero) | C2: 3 | D2: Purchase | F2: =C2*D2*E2 -> #VALUE! | H2: =F2+(F2*G2) -> #VALUE! | K2: 3 | L2: He spins around and whips out a puny dollar-store pocket knife. | M2: Script specifies cheap dollar-store style knife. Multiple units for takes. Armorer required per weapon rules. | N2: High | O2: SCRIPT
A3: 2500.02 | B3: Props - Armorer (knife/weapon on set safety) | C3: 1 | D3: Days | F3: =C3*D3*E3 -> #VALUE! | H3: =F3+(F3*G3) -> #VALUE! | K3: 3 | L3: whips out a puny dollar-store pocket knife. The Man stares at him, knife still in hand. | M3: Knife is present in multiple scenes and brandished/held throughout climax. Armorer legally required on set whenever weapon is present. | N3: High | O3: SCRIPT
A4: 2500.03 | B4: Props - Rosary (hero prop, subtly placed in bag by Brother) | C4: 2 | D4: Purchase | F4: =C4*D4*E4 -> #VALUE! | H4: =F4+(F4*G4) -> #VALUE! | K4: 4 | L4: very subtly slips in a rosary as well | M4: Hero prop rosary. Duplicate unit recommended. Must be clearly visible in close-up if required. | N4: High | O4: SCRIPT
A5: 2500.04 | B5: Props - Crucifix (wall-mounted hero prop, church interior) | C5: 1 | D5: Purchase | F5: =C5*D5*E5 -> #VALUE! | H5: =F5+(F5*G5) -> #VALUE! | K5: 2 | L5: He makes eye contact with a CRUCIFIX on the wall. It watches him. | M5: Featured hero prop with dedicated screen time. Must read clearly on camera from across the church. | N5: High | O5: SCRIPT
A6: 2500.05 | B6: Props - Bag (carried by Man to collect stolen money) | C6: 2 | D6: Purchase | F6: =C6*D6*E6 -> #VALUE! | H6: =F6+(F6*G6) -> #VALUE! | K6: 4 | L6: He stands, bag in hand... Brother places the last of the money in the bag | M6: Bag is a recurring hand prop throughout the script. Duplicate recommended. | N6: High | O6: SCRIPT
A7: 2500.06 | B7: Props - Cigarette / smoking practical (Man smoking in shadows) | C7: 1 | D7: Allow | F7: =C7*D7*E7 -> #VALUE! | H7: =F7+(F7*G7) -> #VALUE! | K7: 2 | L7: cigarette smoke puffs out of the darkness and is illuminated by the streetlight. | M7: Practical cigarettes or herbal cigarette alternatives required. Smoke effect may need coordination with Electric (fog/smoke). | N7: High | O7: SCRIPT
A8: 2500.07 | B8: Props - Church keys (Brother locks door with keys) | C8: 2 | D8: Purchase | F8: =C8*D8*E8 -> #VALUE! | H8: =F8+(F8*G8) -> #VALUE! | K8: 2 | L8: A BROTHER emerges from the church, locks the door with his keys | M8: Practical keys used in action. Duplicate set recommended. | N8: High | O8: SCRIPT
A9: 2500.08 | B9: Property Master | C9: [DEAL] | O9: DEAL
A10: 2500.09 | B10: Assistant Property Master | C10: [DEAL] | O10: DEAL
A11: 2500.10 | B11: Prop rentals | C11: [DEAL] | O11: DEAL
A12: 2500.11 | B12: Prop purchases | C12: [DEAL] | O12: DEAL

Sheet 2600
A1: Account No | B1: Description | C1: Amount | D1: Unit Type | E1: Rate | F1: Subtotal | G1: Fringe % | H1: Total | I1: Vendor | J1: Vendor URL | K1: Script Page | L1: Script Quote | M1: Notes | N1: Confidence | O1: Populated By
A2: 2600.01 | B2: Handheld camera package — INT church entrance sequence | C2: 1 | D2: Rental-Day | F2: =C2*D2*E2 -> #VALUE! | H2: =F2+(F2*G2) -> #VALUE! | K2: 2 | L2: HANDHELD. Frantic cuts. Close-ups of hands picking the locks. | M2: Director calls out handheld explicitly; likely requires fluid head rig and operator | N2: High | O2: SCRIPT
A3: 2600.02 | B3: Additional camera unit — wide/static exterior shots | C3: 1 | D3: Rental-Day | F3: =C3*D3*E3 -> #VALUE! | H3: =F3+(F3*G3) -> #VALUE! | K3: 2 | L3: WIDE. Long take. A small church sits still under streetlight. | M3: Script specifies wide long-take and separate static exterior shots; may require second camera setup | N3: Medium | O3: SCRIPT
A4: 2600.03 | B4: Director of Photography | C4: [DEAL] | O4: DEAL
A5: 2600.04 | B5: Camera Operator | C5: [DEAL] | O5: DEAL
A6: 2600.05 | B6: 1st AC / Focus Puller | C6: [DEAL] | O6: DEAL
A7: 2600.06 | B7: 2nd AC / Loader | C7: [DEAL] | O7: DEAL
A8: 2600.07 | B8: Main Camera Package | C8: [DEAL] | O8: DEAL

Sheet 2700
A1: Account No | B1: Description | C1: Amount | D1: Unit Type | E1: Rate | F1: Subtotal | G1: Fringe % | H1: Total | I1: Vendor | J1: Vendor URL | K1: Script Page | L1: Script Quote | M1: Notes | N1: Confidence | O1: Populated By
A2: 2700.01 | B2: Night exterior lighting package — church exterior | C2: 1 | D2: Rental-Day | F2: =C2*D2*E2 -> #VALUE! | H2: =F2+(F2*G2) -> #VALUE! | K2: 2 | L2: EXT. CHURCH – NIGHT | M2: Full night exterior shoot; streetlight practical must be augmented with grip/electric package | N2: High | O2: SCRIPT
A3: 2700.02 | B3: Dim interior church lighting package | C3: 1 | D3: Rental-Day | F3: =C3*D3*E3 -> #VALUE! | H3: =F3+(F3*G3) -> #VALUE! | K3: 2 | L3: The Man moves through the dim interior. | M3: Low-key motivated lighting required to match described dim church interior at night | N3: High | O3: SCRIPT
A4: 2700.03 | B4: Practical streetlight — motivated exterior source | C4: 1 | D4: Rental-Day | F4: =C4*D4*E4 -> #VALUE! | H4: =F4+(F4*G4) -> #VALUE! | K4: 2 | L4: cigarette smoke puffs out of the darkness and is illuminated by the streetlight. | M4: Streetlight is a scripted story element used to illuminate smoke; may need practical swap or supplemental unit | N4: High | O4: SCRIPT
A5: 2700.04 | B5: Gaffer | C5: [DEAL] | O5: DEAL
A6: 2700.05 | B6: Best Boy Electric | C6: [DEAL] | O6: DEAL
A7: 2700.06 | B7: Electricians | C7: [DEAL] | O7: DEAL
A8: 2700.07 | B8: Lighting Package | C8: [DEAL] | O8: DEAL
A9: 2700.08 | B9: Generator rental | C9: [DEAL] | O9: DEAL

Sheet 2800
A1: Account No | B1: Description | C1: Amount | D1: Unit Type | E1: Rate | F1: Subtotal | G1: Fringe % | H1: Total | I1: Vendor | J1: Vendor URL | K1: Script Page | L1: Script Quote | M1: Notes | N1: Confidence | O1: Populated By
A2: 2800.01 | B2: Key Grip | C2: [DEAL] | O2: DEAL
A3: 2800.02 | B3: Best Boy Grip | C3: [DEAL] | O3: DEAL
A4: 2800.03 | B4: Dolly Grip | C4: [DEAL] | O4: DEAL
A5: 2800.04 | B5: Grip Package | C5: [DEAL] | O5: DEAL

Sheet 2900
A1: Account No | B1: Description | C1: Amount | D1: Unit Type | E1: Rate | F1: Subtotal | G1: Fringe % | H1: Total | I1: Vendor | J1: Vendor URL | K1: Script Page | L1: Script Quote | M1: Notes | N1: Confidence | O1: Populated By
A2: 2900.01 | B2: Production Sound Mixer | C2: [DEAL] | O2: DEAL
A3: 2900.02 | B3: Boom Operator | C3: [DEAL] | O3: DEAL
A4: 2900.03 | B4: Sound Package | C4: [DEAL] | O4: DEAL
A5: 2900.04 | B5: Walkie-talkies | C5: [DEAL] | O5: DEAL

Sheet 3000
A1: Account No | B1: Description | C1: Amount | D1: Unit Type | E1: Rate | F1: Subtotal | G1: Fringe % | H1: Total | I1: Vendor | J1: Vendor URL | K1: Script Page | L1: Script Quote | M1: Notes | N1: Confidence | O1: Populated By
A2: 3000.01 | B2: Stunt coordinator — physical grab/shoulder restraint between actors | C2: 1 | D2: Days | F2: =C2*D2*E2 -> #VALUE! | H2: =F2+(F2*G2) -> #VALUE! | K2: 4 | L2: He stops the Man and grabs his shoulders. Firm, strong, but not violent. | M2: Physical contact between actors legally requires stunt coordinator on set; also covers hug with knife in hand | N2: High | O2: SCRIPT
A3: 3000.02 | B3: Safety officer — knife handling on set (pocket knife prop) | C3: 1 | D3: Days | F3: =C3*D3*E3 -> #VALUE! | H3: =F3+(F3*G3) -> #VALUE! | K3: 3 | L3: He spins around and whips out a puny dollar-store pocket knife. | M3: Weapon present throughout multiple pages; knife brandished, held during hug — safety officer and armorer protocol required | N3: High | O3: SCRIPT
A4: 3000.03 | B4: FX Coordinator | C4: [DEAL] | O4: DEAL
A5: 3000.04 | B5: FX Crew | C5: [DEAL] | O5: DEAL
A6: 3000.05 | B6: FX Materials / consumables | C6: [DEAL] | O6: DEAL

Sheet 3100
A1: Account No | B1: Description | C1: Amount | D1: Unit Type | E1: Rate | F1: Subtotal | G1: Fringe % | H1: Total | I1: Vendor | J1: Vendor URL | K1: Script Page | L1: Script Quote | M1: Notes | N1: Confidence | O1: Populated By
A2: 3100.01 | B2: VFX Supervisor | C2: [DEAL] | O2: DEAL
A3: 3100.02 | B3: VFX Production / labor | C3: [DEAL] | O3: DEAL
A4: 3100.03 | B4: VFX Software / tools | C4: [DEAL] | O4: DEAL

Sheet 3200
A1: Account No | B1: Description | C1: Amount | D1: Unit Type | E1: Rate | F1: Subtotal | G1: Fringe % | H1: Total | I1: Vendor | J1: Vendor URL | K1: Script Page | L1: Script Quote | M1: Notes | N1: Confidence | O1: Populated By
A2: 3200.01 | B2: Set Carpenter (standby) | C2: [SCHEDULE] | O2: SCHEDULE
A3: 3200.02 | B3: Standby Painter | C3: [SCHEDULE] | O3: SCHEDULE
A4: 3200.03 | B4: Craft Service | C4: [SCHEDULE] | O4: SCHEDULE
A5: 3200.04 | B5: First Aid / On-set Nurse | C5: [SCHEDULE] | O5: SCHEDULE
A6: 3200.05 | B6: Security | C6: [SCHEDULE] | O6: SCHEDULE

Sheet 3300
A1: Account No | B1: Description | C1: Amount | D1: Unit Type | E1: Rate | F1: Subtotal | G1: Fringe % | H1: Total | I1: Vendor | J1: Vendor URL | K1: Script Page | L1: Script Quote | M1: Notes | N1: Confidence | O1: Populated By
A2: 3300.01 | B2: Wardrobe – The Man: disheveled, raggy, worn clothing | C2: 1 | D2: Allow | F2: =C2*D2*E2 -> #VALUE! | H2: =F2+(F2*G2) -> #VALUE! | K2: 2 | L2: Disheveled. Raggy clothes. Poorly shaven. | M2: Character requires distressed, worn wardrobe to convey homelessness/destitution. Single costume throughout. | N2: High | O2: SCRIPT
A3: 3300.02 | B3: Wardrobe – The Brother: religious habit/clerical dress | C3: 1 | D3: Allow | F3: =C3*D3*E3 -> #VALUE! | H3: =F3+(F3*G3) -> #VALUE! | K3: 2 | L3: A BROTHER emerges from the church, locks the door with his keys | M3: Character identified as a religious Brother; requires appropriate clerical or monastic habit. | N3: High | O3: SCRIPT
A4: 3300.03 | B4: Costume Designer | C4: [DEAL] | O4: DEAL
A5: 3300.04 | B5: Wardrobe Supervisor | C5: [DEAL] | O5: DEAL
A6: 3300.05 | B6: Costumer(s) | C6: [DEAL] | O6: DEAL
A7: 3300.06 | B7: Wardrobe Rental | C7: [DEAL] | O7: DEAL
A8: 3300.07 | B8: Wardrobe Purchases | C8: [DEAL] | O8: DEAL
A9: 3300.08 | B9: Dry cleaning / laundry | C9: [DEAL] | O9: DEAL

Sheet 3400
A1: Account No | B1: Description | C1: Amount | D1: Unit Type | E1: Rate | F1: Subtotal | G1: Fringe % | H1: Total | I1: Vendor | J1: Vendor URL | K1: Script Page | L1: Script Quote | M1: Notes | N1: Confidence | O1: Populated By
A2: 3400.01 | B2: Makeup & Hair – The Man: stubble/poorly shaven look, sweat effect | C2: 1 | D2: Allow | F2: =C2*D2*E2 -> #VALUE! | H2: =F2+(F2*G2) -> #VALUE! | K2: 2 | L2: Poorly shaven. His face is flustered, sweating, desperate, and angry. | M2: Script explicitly calls out poorly shaven face and sweating; requires makeup application for stubble and perspiration effect. | N2: High | O2: SCRIPT
A3: 3400.02 | B3: Head Makeup Artist | C3: [DEAL] | O3: DEAL
A4: 3400.03 | B4: Key Hair Stylist | C4: [DEAL] | O4: DEAL
A5: 3400.04 | B5: Additional Makeup / Hair | C5: [DEAL] | O5: DEAL
A6: 3400.05 | B6: Makeup Supplies | C6: [DEAL] | O6: DEAL

Sheet 3500
A1: Account No | B1: Description | C1: Amount | D1: Unit Type | E1: Rate | F1: Subtotal | G1: Fringe % | H1: Total | I1: Vendor | J1: Vendor URL | K1: Script Page | L1: Script Quote | M1: Notes | N1: Confidence | O1: Populated By
A2: 3500.01 | B2: Locations – Permit & fees: EXT. Church exterior, public/street-facing location, NIGHT | C2: 1 | D2: Allow | F2: =C2*D2*E2 -> #VALUE! | H2: =F2+(F2*G2) -> #VALUE! | K2: 2 | L2: EXT. CHURCH – NIGHT A small church sits still under streetlight. | M2: Exterior church on a public street at night requires location permit, parking, and possible street use fees. Streetlight referenced implies public right-of-way. | N2: High | O2: SCRIPT
A3: 3500.02 | B3: Locations – Church interior rental (INT. CHURCH / INT. CHURCH ENTRANCE) | C3: 1 | D3: Rental-Day | F3: =C3*D3*E3 -> #VALUE! | H3: =F3+(F3*G3) -> #VALUE! | K3: 2 | L3: INT. CHURCH ENTRANCE – CONTINUOUS… INT. CHURCH – CONTINUOUS | M3: Multiple interior church scenes require facility rental agreement with the church or suitable substitute location. | N3: High | O3: SCRIPT
A4: 3500.03 | B4: Location Manager | C4: [DEAL] | O4: DEAL
A5: 3500.04 | B5: Location Scout / Survey | C5: [DEAL] | O5: DEAL
A6: 3500.05 | B6: Police / fire standby | C6: [DEAL] | O6: DEAL
A7: 3500.06 | B7: Catering | C7: [DEAL] | O7: DEAL
A8: 3500.07 | B8: Parking / logistics | C8: [DEAL] | O8: DEAL

Sheet 3600
A1: Account No | B1: Description | C1: Amount | D1: Unit Type | E1: Rate | F1: Subtotal | G1: Fringe % | H1: Total | I1: Vendor | J1: Vendor URL | K1: Script Page | L1: Script Quote | M1: Notes | N1: Confidence | O1: Populated By
A2: 3600.01 | B2: Transportation Coordinator | C2: [SCHEDULE] | O2: SCHEDULE
A3: 3600.02 | B3: Captain Driver | C3: [SCHEDULE] | O3: SCHEDULE
A4: 3600.03 | B4: Drivers | C4: [SCHEDULE] | O4: SCHEDULE
A5: 3600.04 | B5: Production vehicles (trucks / vans) | C5: [DEAL] | O5: DEAL
A6: 3600.05 | B6: Honeywagon / basecamp | C6: [DEAL] | O6: DEAL

Sheet 3800
A1: Account No | B1: Description | C1: Amount | D1: Unit Type | E1: Rate | F1: Subtotal | G1: Fringe % | H1: Total | I1: Vendor | J1: Vendor URL | K1: Script Page | L1: Script Quote | M1: Notes | N1: Confidence | O1: Populated By
A2: 3800.01 | B2: Stage rental | C2: [DEAL] | O2: DEAL
A3: 3800.02 | B3: Back lot rental | C3: [DEAL] | O3: DEAL
A4: 3800.03 | B4: Electric power (stage) | C4: [DEAL] | O4: DEAL
A5: 3800.04 | B5: Heating / AC | C5: [DEAL] | O5: DEAL

Sheet 3900
A1: Account No | B1: Description | C1: Amount | D1: Unit Type | E1: Rate | F1: Subtotal | G1: Fringe % | H1: Total | I1: Vendor | J1: Vendor URL | K1: Script Page | L1: Script Quote | M1: Notes | N1: Confidence | O1: Populated By
A2: 3900.01 | B2: Extras Casting fee | C2: [DEAL] | O2: DEAL
A3: 3900.02 | B3: Stand-ins | C3: [SCHEDULE] | O3: SCHEDULE
A4: 3900.03 | B4: Welfare Worker / Teacher (minors) | C4: [DEAL] | O4: DEAL

Sheet 5100
A1: Account No | B1: Description | C1: Amount | D1: Unit Type | E1: Rate | F1: Subtotal | G1: Fringe % | H1: Total | I1: Vendor | J1: Vendor URL | K1: Script Page | L1: Script Quote | M1: Notes | N1: Confidence | O1: Populated By
A2: 5100.01 | B2: Post Production Supervisor | C2: [DEAL] | O2: DEAL
A3: 5100.02 | B3: Editor | C3: [DEAL] | O3: DEAL
A4: 5100.03 | B4: Assistant Editor(s) | C4: [DEAL] | O4: DEAL
A5: 5100.04 | B5: Editing Room / Avid rental | C5: [DEAL] | O5: DEAL

Sheet 5200
A1: Account No | B1: Description | C1: Amount | D1: Unit Type | E1: Rate | F1: Subtotal | G1: Fringe % | H1: Total | I1: Vendor | J1: Vendor URL | K1: Script Page | L1: Script Quote | M1: Notes | N1: Confidence | O1: Populated By
A2: 5200.01 | B2: Color grading / Digital Intermediate | C2: [DEAL] | O2: DEAL
A3: 5200.02 | B3: Digital deliverables | C3: [DEAL] | O3: DEAL
A4: 5200.03 | B4: Archival / backup | C4: [DEAL] | O4: DEAL

Sheet 5300
A1: Account No | B1: Description | C1: Amount | D1: Unit Type | E1: Rate | F1: Subtotal | G1: Fringe % | H1: Total | I1: Vendor | J1: Vendor URL | K1: Script Page | L1: Script Quote | M1: Notes | N1: Confidence | O1: Populated By
A2: 5300.01 | B2: Sound Designer | C2: [DEAL] | O2: DEAL
A3: 5300.02 | B3: Foley Artist + Studio | C3: [DEAL] | O3: DEAL
A4: 5300.03 | B4: ADR / Looping | C4: [DEAL] | O4: DEAL
A5: 5300.04 | B5: Final Mix | C5: [DEAL] | O5: DEAL

Sheet 5400
A1: Account No | B1: Description | C1: Amount | D1: Unit Type | E1: Rate | F1: Subtotal | G1: Fringe % | H1: Total | I1: Vendor | J1: Vendor URL | K1: Script Page | L1: Script Quote | M1: Notes | N1: Confidence | O1: Populated By
A2: 5400.01 | B2: Composer fee | C2: [DEAL] | O2: DEAL
A3: 5400.02 | B3: Musicians / orchestration | C3: [DEAL] | O3: DEAL
A4: 5400.03 | B4: Music rights / licensing | C4: [DEAL] | O4: DEAL
A5: 5400.04 | B5: Score recording studio | C5: [DEAL] | O5: DEAL

Sheet 5500
A1: Account No | B1: Description | C1: Amount | D1: Unit Type | E1: Rate | F1: Subtotal | G1: Fringe % | H1: Total | I1: Vendor | J1: Vendor URL | K1: Script Page | L1: Script Quote | M1: Notes | N1: Confidence | O1: Populated By
A2: 5500.01 | B2: Main titles design | C2: [DEAL] | O2: DEAL
A3: 5500.02 | B3: End credits | C3: [DEAL] | O3: DEAL
A4: 5500.03 | B4: Title card mastering | C4: [DEAL] | O4: DEAL

Sheet 5600
A1: Account No | B1: Description | C1: Amount | D1: Unit Type | E1: Rate | F1: Subtotal | G1: Fringe % | H1: Total | I1: Vendor | J1: Vendor URL | K1: Script Page | L1: Script Quote | M1: Notes | N1: Confidence | O1: Populated By
A2: 5600.01 | B2: Opticals / visual effects (post) | C2: [DEAL] | O2: DEAL
A3: 5600.02 | B3: Digital intermediate (opticals) | C3: [DEAL] | O3: DEAL

Sheet 5700
A1: Account No | B1: Description | C1: Amount | D1: Unit Type | E1: Rate | F1: Subtotal | G1: Fringe % | H1: Total | I1: Vendor | J1: Vendor URL | K1: Script Page | L1: Script Quote | M1: Notes | N1: Confidence | O1: Populated By
A2: 5700.01 | B2: Video deliverables / mastering | C2: [DEAL] | O2: DEAL
A3: 5700.02 | B3: Streaming / broadcast specs | C3: [DEAL] | O3: DEAL

Sheet 6100
A1: Account No | B1: Description | C1: Amount | D1: Unit Type | E1: Rate | F1: Subtotal | G1: Fringe % | H1: Total | I1: Vendor | J1: Vendor URL | K1: Script Page | L1: Script Quote | M1: Notes | N1: Confidence | O1: Populated By
A2: 6100.01 | B2: Cast insurance | C2: [DEAL] | O2: DEAL
A3: 6100.02 | B3: Negative / production insurance | C3: [DEAL] | O3: DEAL
A4: 6100.03 | B4: E&O insurance | C4: [DEAL] | O4: DEAL
A5: 6100.04 | B5: General liability | C5: [DEAL] | O5: DEAL

Sheet 6200
A1: Account No | B1: Description | C1: Amount | D1: Unit Type | E1: Rate | F1: Subtotal | G1: Fringe % | H1: Total | I1: Vendor | J1: Vendor URL | K1: Script Page | L1: Script Quote | M1: Notes | N1: Confidence | O1: Populated By
A2: 6200.01 | B2: Legal fees | C2: [DEAL] | O2: DEAL
A3: 6200.02 | B3: Contract preparation | C3: [DEAL] | O3: DEAL
A4: 6200.03 | B4: Clearances / chain of title | C4: [DEAL] | O4: DEAL

Sheet 6300
A1: Account No | B1: Description | C1: Amount | D1: Unit Type | E1: Rate | F1: Subtotal | G1: Fringe % | H1: Total | I1: Vendor | J1: Vendor URL | K1: Script Page | L1: Script Quote | M1: Notes | N1: Confidence | O1: Populated By
A2: 6300.01 | B2: Unit Publicist | C2: [DEAL] | O2: DEAL
A3: 6300.02 | B3: Electronic Press Kit (EPK) | C3: [DEAL] | O3: DEAL
A4: 6300.03 | B4: Stills photographer | C4: [DEAL] | O4: DEAL

Sheet 6400
A1: Account No | B1: Description | C1: Amount | D1: Unit Type | E1: Rate | F1: Subtotal | G1: Fringe % | H1: Total | I1: Vendor | J1: Vendor URL | K1: Script Page | L1: Script Quote | M1: Notes | N1: Confidence | O1: Populated By
A2: 6400.01 | B2: Accounting / payroll fees | C2: [DEAL] | O2: DEAL
A3: 6400.02 | B3: Bank charges | C3: [DEAL] | O3: DEAL
A4: 6400.03 | B4: Completion bond (~2.5% of budget) | C4: [DEAL] | O4: DEAL
